{
    "name":"Level Order Balanced",
    "description":"Balanced settings for Level Order Randomizer.",
    "fast_start_beginning_of_game":true,
    "unlock_all_moves":false,
    "enemy_rando":true,
    "krool_phase_order_rando":true,
    "boss_kong_rando":true,
    "boss_location_rando":true,
    "random_medal_requirement":false,
    "bananaport_rando":false,
    "kasplat_rando":true,
    "kong_rando":true,
    "shop_location_rando":true,
    "random_prices":"low",
    "level_randomization":"level_order",
    "randomize_blocker_required_amounts":true,
    "randomize_cb_required_amounts":true,
    "blocker_text":"50",
    "troff_text":"200",
    "unlock_fairy_shockwave":false,
    "crown_door_open":true,
    "coin_door_open":true,
    "bonus_barrel_rando":false,
    "gnawty_barrels":false,
    "bonus_barrel_auto_complete":true,
    "open_lobbies":false,
    "krool_random":false,
    "krool_phase_count":3,
    "krool_access":true,
    "keys_random":false,
    "krool_key_count":3,
    "starting_random":false,
    "starting_kongs_count":3,
    "quality_of_life":true,
    "enable_tag_anywhere":true,
    "wrinkly_hints":"standard",
    "disable_shop_hints":false,
    "warp_to_isles":true,
    "helm_setting":"skip_all",
    "portal_numbers":true,
    "shop_indicator":true
 }