{
    "name": "Suggested",
    "description": "Suggested default options for randomization",
    "shuffle_levels": true,
    "k_rool_phase_order": true,
    "boss_kong_rando": true,
    "boss_location_rando": true,
    "bonus_barrel_rando": true,
    "blocker_0": 0,
    "troff_0": 0,
    "blocker_1": 0,
    "troff_1": 0,
    "blocker_2": 0,
    "troff_2": 0,
    "blocker_3": 0,
    "troff_3": 0,
    "blocker_4": 0,
    "troff_4": 0,
    "blocker_5": 0,
    "troff_5": 0,
    "blocker_6": 0,
    "troff_6": 0,
    "blocker_7": 0,
    "crown_door_open": true,
    "coin_door_open": true,
    "fast_start_beginning_of_game": true,
    "quality_of_life": true,
    "fast_start_hideout_helm": true,
    "enemy_rando": true,
    "kasplat_rando": true,
    "shop_location_rando": true,
    "bananaport_rando": true,
    "enable_tag_anywhere": true,
    "wrinkly_hints": true,
    "portal_numbers": true,
    "randomize_blocker_required_amounts": true,
    "randomize_cb_required_amounts": true,
    "generate_spoilerlog": true,
    "warp_to_isles": true,
    "shop_indicator": true
  }
  